iif_processor
