Metadata-Version: 1.0
Name: iif-processor
Version: 0.2
Summary: Processes all images in a directory for IIF server
Home-page: http://github.com/j0hnds/diva.js
Author: Dave Sieh
Author-email: dj0nve@gmail.com
License: MIT
Platform: UNKNOWN
